{
  "target_repo": {
    "url": "https://github.com/MicrosoftDocs/azure-docs-sdk-node",
    "branch": "smoke-test",
    "folder": "preview-packages"
  },
  "npm_package_sources": [
    {
      "name": "@azure/core-tracing@dev"
    },
    {
      "name": "@azure/keyvault-certificates@dev"
    },
    {
      "name": "@azure/keyvault-keys@dev"
    },
    {
      "name": "@azure/keyvault-secrets@dev"
    },
    {
      "name": "@azure/identity@dev"
    },
    {
      "name": "@azure/schema-registry@dev"
    },
    {
      "name": "@azure/data-tables@dev"
    },
    {
      "name": "@azure/schema-registry-avro@dev"
    },
    {
      "name": "@azure/keyvault-admin@dev"
    },
    {
      "name": "@azure/storage-blob-changefeed@dev"
    },
    {
      "name": "@azure/ai-anomaly-detector@dev"
    },
    {
      "name": "@azure/ai-text-analytics@dev"
    },
    {
      "name": "@azure/communication-sms@dev"
    },
    {
      "name": "@azure/communication-common@dev"
    },
    {
      "name": "@azure/communication-chat@dev"
    },
    {
      "name": "@azure/communication-administration@dev"
    },
    {
      "name": "@azure/eventgrid@dev"
    },
    {
      "name": "@azure/search-documents@dev"
    },
    {
      "name": "@azure/ai-metrics-advisor@dev"
    },
    {
      "name": "@azure/digital-twins-core@dev"
    },
    {
      "name": "@azure/core-amqp@dev"
    },
    {
      "name": "@azure/ai-form-recognizer@dev"
    },
    {
      "name": "@azure/synapse-artifacts@dev"
    },
    {
      "name": "@azure/storage-file-datalake@dev"
    },
    {
      "name": "@azure/synapse-monitoring@dev"
    },
    {
      "name": "@azure/synapse-access-control@dev"
    },
    {
      "name": "@azure/synapse-managed-private-endpoints@dev"
    },
    {
      "name": "@azure/synapse-spark@dev"
    },
    {
      "name": "@azure/storage-file-share@dev"
    },
    {
      "name": "@azure/storage-blob@dev"
    },
    {
      "name": "@azure/storage-queue@dev"
    },
    {
      "name": "@azure/opentelemetry-exporter-azure-monitor@dev"
    },
    {
      "name": "@azure/attestation@dev"
    }
  ],
  "source_repos": []
}
